heatprofile/__init__.py
heatprofile/heatprofile.py
heatprofile/heatprofiler_json_dump.py
heatprofile-0.0.11.dist-info/LICENSE
heatprofile-0.0.11.dist-info/METADATA
heatprofile-0.0.11.dist-info/WHEEL
heatprofile-0.0.11.dist-info/top_level.txt
heatprofile-0.0.11.dist-info/RECORD
