Metadata-Version: 2.1
Name: heatprofile
Version: 0.0.11
Summary: A simple tool for giving immediate visual feedback on the hotspots in your code.
Author-email: Samuel Jakes <sampcjakes@gmail.com>
Project-URL: Homepage, https://github.com/SamuelJakes/heatprofile
Project-URL: Issues, https://github.com/SamuelJakes/heatprofile/issues
Classifier: Programming Language :: Python :: 3
Classifier: License :: OSI Approved :: MIT License
Classifier: Operating System :: OS Independent
Requires-Python: >=3.8
License-File: LICENSE
Requires-Dist: psutil >=5.9.6
